{"success":true,"build":{"name":"Gharlan Ironheart","class":"Barbarian","dualClass":null,"level":7,"ancestry":"Dwarf","heritage":"Strong-Blooded Dwarf","background":"Warrior","alignment":"LE","gender":"M","age":"136","deity":"The Keeper ","size":2,"sizeName":"Medium","keyability":"str","languages":["Common","Dwarven"],"rituals":[],"resistances":[],"inventorMods":[],"attributes":{"ancestryhp":10,"classhp":12,"bonushp":0,"bonushpPerLevel":0,"speed":20,"speedBonus":0},"abilities":{"str":18,"dex":14,"con":18,"int":10,"wis":16,"cha":10,"breakdown":{"ancestryFree":["Str"],"ancestryBoosts":["Con","Wis"],"ancestryFlaws":["Cha"],"backgroundBoosts":["Con","Str"],"classBoosts":["Str"],"mapLevelledBoosts":{"1":["Str","Dex","Con","Wis"],"5":["Con","Wis","Dex","Cha"]}}},"proficiencies":{"classDC":2,"perception":4,"fortitude":6,"reflex":2,"will":4,"heavy":0,"medium":2,"light":2,"unarmored":2,"advanced":0,"martial":4,"simple":4,"unarmed":4,"castingArcane":0,"castingDivine":0,"castingOccult":0,"castingPrimal":0,"acrobatics":0,"arcana":0,"athletics":2,"crafting":0,"deception":0,"diplomacy":0,"intimidation":6,"medicine":0,"nature":4,"occultism":0,"performance":0,"religion":2,"society":0,"stealth":0,"survival":2,"thievery":0},"mods":{},"feats":[["Intimidating Glare",null,"Awarded Feat",1],["Intimidating Glare",null,"Awarded Feat",2],["Strong-Blooded Dwarf",null,"Heritage",1,"Heritage Feat","standardChoice",null],["Dwarven Doughtiness",null,"Ancestry Feat",1,"Dwarf Feat 1","standardChoice",null],["Sudden Charge",null,"Class Feat",1,"Barbarian Feat 1","standardChoice",null],["Experienced Tracker",null,"Skill Feat",2,"Skill Feat 2","standardChoice",null],["Raging Intimidation",null,"Class Feat",2,"Barbarian Feat 2","standardChoice",null],["Intimidating Prowess",null,"General Feat",3,"General Feat 3","standardChoice",null],["Natural Medicine",null,"Skill Feat",4,"Skill Feat 4","standardChoice",null],["Fast Movement",null,"Class Feat",4,"Barbarian Feat 4","standardChoice",null],["Defy the Darkness",null,"Ancestry Feat",5,"Dwarf Feat 5","standardChoice",null],["Quick Jump",null,"Skill Feat",6,"Skill Feat 6","standardChoice",null],["Attack of Opportunity",null,"Class Feat",6,"Barbarian Feat 6","standardChoice",null],["Battle Cry",null,"General Feat",7,"General Feat 7","standardChoice",null]],"specials":["Rage","Bestial Rage (Instinct Ability)","Ape","Animal Instinct","Darkvision","Deny Advantage","Brutality","Juggernaut","Animal Instinct Specialization Ability","Weapon Specialization","Strong-Blooded Dwarf"],"lores":[["Warfare",2]],"equipmentContainers":{"1af8d25a-943b-4c5e-bff8-00a4e4778506":{"containerName":"Backpack","bagOfHolding":false,"backpack":true}},"equipment":[["Backpack",1,"Invested"],["Bedroll",1,"1af8d25a-943b-4c5e-bff8-00a4e4778506","Invested"],["Chalk",10,"1af8d25a-943b-4c5e-bff8-00a4e4778506","Invested"],["Flint and Steel",1,"1af8d25a-943b-4c5e-bff8-00a4e4778506","Invested"],["Rope",1,"1af8d25a-943b-4c5e-bff8-00a4e4778506","Invested"],["Rations",2,"1af8d25a-943b-4c5e-bff8-00a4e4778506","Invested"],["Torch",5,"1af8d25a-943b-4c5e-bff8-00a4e4778506","Invested"],["Waterskin",1,"1af8d25a-943b-4c5e-bff8-00a4e4778506","Invested"],["Soap",1,"1af8d25a-943b-4c5e-bff8-00a4e4778506","Invested"],["Grappling Hook",1,"Invested"],["Handwraps of Mighty Blows (+1 Striking)",1,"Invested"]],"specificProficiencies":{"trained":[],"expert":[],"master":[],"legendary":[]},"weapons":[{"name":"Special Unarmed (1d10)","qty":1,"prof":"unarmed","die":"d12","pot":1,"str":"striking","mat":null,"display":"+1 Striking Gorilla Fist (+)","runes":[],"damageType":"B, P or S","attack":16,"damageBonus":11,"extraDamage":[],"increasedDice":true,"isInventor":false},{"name":"Javelin","qty":4,"prof":"simple","die":"d6","pot":0,"str":"","mat":null,"display":"Javelin (x4)","runes":[],"damageType":"P","attack":13,"damageBonus":6,"extraDamage":[],"increasedDice":false,"isInventor":false},{"name":"Fist","qty":1,"prof":"unarmed","die":"d4","pot":0,"str":"","mat":null,"display":"Fist","runes":[],"damageType":"B","attack":15,"damageBonus":6,"extraDamage":[],"increasedDice":false,"isInventor":false}],"money":{"cp":0,"sp":0,"gp":15,"pp":0},"armor":[{"name":"Hide","qty":1,"prof":"medium","pot":0,"res":"","mat":null,"display":"Hide","worn":true,"runes":[]}],"spellCasters":[],"focusPoints":0,"focus":{},"formula":[],"acTotal":{"acProfBonus":9,"acAbilityBonus":2,"acItemBonus":3,"acTotal":24,"shieldBonus":null},"pets":[],"familiars":[]}}